azure/communication/jobrouter/__init__.py
azure/communication/jobrouter/_api_versions.py
azure/communication/jobrouter/_client.py
azure/communication/jobrouter/_configuration.py
azure/communication/jobrouter/_model_base.py
azure/communication/jobrouter/_patch.py
azure/communication/jobrouter/_serialization.py
azure/communication/jobrouter/_vendor.py
azure/communication/jobrouter/_version.py
azure/communication/jobrouter/py.typed
azure/communication/jobrouter/_operations/__init__.py
azure/communication/jobrouter/_operations/_operations.py
azure/communication/jobrouter/_operations/_patch.py
azure/communication/jobrouter/_shared/__init__.py
azure/communication/jobrouter/_shared/auth_policy_utils.py
azure/communication/jobrouter/_shared/models.py
azure/communication/jobrouter/_shared/policy.py
azure/communication/jobrouter/_shared/user_credential.py
azure/communication/jobrouter/_shared/user_credential_async.py
azure/communication/jobrouter/_shared/utils.py
azure/communication/jobrouter/_shared/utils_async.py
azure/communication/jobrouter/aio/__init__.py
azure/communication/jobrouter/aio/_client.py
azure/communication/jobrouter/aio/_configuration.py
azure/communication/jobrouter/aio/_patch.py
azure/communication/jobrouter/aio/_vendor.py
azure/communication/jobrouter/aio/_operations/__init__.py
azure/communication/jobrouter/aio/_operations/_operations.py
azure/communication/jobrouter/aio/_operations/_patch.py
azure/communication/jobrouter/models/__init__.py
azure/communication/jobrouter/models/_enums.py
azure/communication/jobrouter/models/_models.py
azure/communication/jobrouter/models/_patch.py
azure_communication_jobrouter-1.0.0.dist-info/LICENSE
azure_communication_jobrouter-1.0.0.dist-info/METADATA
azure_communication_jobrouter-1.0.0.dist-info/WHEEL
azure_communication_jobrouter-1.0.0.dist-info/top_level.txt
azure_communication_jobrouter-1.0.0.dist-info/RECORD
